[
    {
        "date": "2025-10-16",
        "day": "Thursday",
        "breakfast": [
            "Choice of Egg",
            "Cornflakes",
            "Bread + Jam",
            "Misal and Pav",
            "Sweet Daliya",
            "Cut Onion Lemon",
            "Honey Dew",
            "Tea + Coffee",
            "Milk"
        ],
        "lunch": [
            "Appalam Papad",
            "Soya Handi",
            "Dahi Kadhi Pakoda",
            "Veg Khichdi",
            "Chapati",
            "Plain Rice",
            "Sambar",
            "Rooh Afza"
        ],
        "dinner": [
            "Khimchi Salad",
            "Veg Manchurian",
            "Dal Makhani",
            "Chapati",
            "EGG/Veg Fried Rice",
            "Rasam",
            "Fruit Custard"
        ]
    },
    {
        "date": "2025-10-17",
        "day": "Friday",
        "breakfast": [
            "Choice of Egg",
            "Cornflakes",
            "Bread + Jam",
            "Seviya Upma",
            "Adrak Chutney",
            "Papaya",
            "Tea + Coffee",
            "Milk"
        ],
        "lunch": [
            "Corn Salad (Seprate)",
            "Kala Chana Masala Dry",
            "Aloo Bhaji Rassa",
            "Dal Panchratan",
            "Bedmi Puri/Chapati",
            "Plain Rice",
            "Sambar",
            "Masala Chaas"
        ],
        "dinner": [
            "Coconut Chutney",
            "Medu Wada",
            "Sambhar",
            "Masala Dosa",
            "Lemon Rice"
        ]
    },
    {
        "date": "2025-10-18",
        "day": "Saturday",
        "breakfast": [
            "Choice of Egg",
            "Cornflakes",
            "Bread + Jam",
            "Poha",
            "Sev",
            "Cut Onion Lemon",
            "Apple",
            "Tea + Coffee",
            "Milk"
        ],
        "lunch": [
            "Crispy Corn",
            "Ragda Mutter",
            "Curd/Butter",
            "Mix Veg Paratha",
            "Plain Rice",
            "Sambar",
            "Mix Blast"
        ],
        "dinner": [
            "Green Salad",
            "Papad Mangodi",
            "Dal Tadka",
            "Chapati",
            "Plain Rice",
            "Rasam",
            "Hot Choco Milk"
        ]
    },
    {
        "date": "2025-10-19",
        "day": "Sunday",
        "breakfast": [
            "Choice of Egg",
            "Cornflakes",
            "Bread + Jam",
            "Masala Dosa ( Live)",
            "Sambhar",
            "Coconut Chutney",
            "Banana",
            "Tea + Coffee",
            "Milk"
        ],
        "lunch": [
            "Onion Salad",
            "Paneer Tikka Masala",
            "Butter Chicken",
            "Naan/Chapati",
            "Biryani Rice",
            "Boondi Raita",
            "Black Current I/C"
        ],
        "dinner": [
            "Macroni Salad (No Cucumber)",
            "Sev Tomato",
            "Aarhar Dal Tadka",
            "Chapati",
            "Plain Rice",
            "Rasam"
        ]
    },
    {
        "date": "2025-10-20",
        "day": "Monday",
        "breakfast": [
            "Choice of Egg",
            "Cornflakes",
            "Bread + Jam",
            "Masala S/W",
            "Tomato Ketchup",
            "Sweet Daliya",
            "Pineapple",
            "Tea + Coffee",
            "Milk"
        ],
        "lunch": [
            "Corn Chees Balls",
            "Paneer Lababdar",
            "Dal Makhani",
            "Tikona Paratha",
            "Kashmiri Pulao",
            "Burhani Raita",
            "Keshari Sheera",
            "Khas Sharbet"
        ],
        "dinner": []
    },
    {
        "date": "2025-10-21",
        "day": "Tuesday",
        "breakfast": [
            "Mix Sprout",
            "Cornflakes",
            "Bread + Jam",
            "Gobhi Paratha",
            "Mixed Pickle",
            "Curd",
            "Honey Dew",
            "Tea + Coffee",
            "Milk"
        ],
        "lunch": [
            "Roasted Papad",
            "Raw Banana Masala",
            "Pakoda Kadhi",
            "Veg Khidchi",
            "Chapati",
            "Plain Rice",
            "Sambar",
            "Rose Lemonade"
        ],
        "dinner": [
            "Lemon + Onion",
            "Bhaji",
            "Dal Fry",
            "PAV/Chapati",
            "Jeera Rice",
            "Rasam",
            "Sahi Tukda"
        ]
    },
    {
        "date": "2025-10-22",
        "day": "Wednesday",
        "breakfast": [
            "Choice of Egg",
            "Cornflakes",
            "Bread + Jam",
            "Rawa Idli",
            "Sambar",
            "Coconut Chutney",
            "Papaya",
            "Tea + Coffee",
            "Milk"
        ],
        "lunch": [
            "Onion Salad",
            "Palak Paneer",
            "Dal Makhani",
            "Chapati",
            "Peas Pulao",
            "Sambar",
            "Mix Veg Raita"
        ],
        "dinner": [
            "Green Salad",
            "Kathal Masala",
            "Dal Maharani",
            "Plain Rice",
            "Chapati",
            "Rasam",
            "Rose Phirni"
        ]
    },
    {
        "date": "2025-10-23",
        "day": "Thursday",
        "breakfast": [
            "Choice of Egg",
            "Cornflakes",
            "Bread + Jam",
            "Palak Puri",
            "Aloo Bhaji",
            "Cut Onion Lemon",
            "Apple",
            "Tea + Coffee",
            "Milk"
        ],
        "lunch": [
            "Bhel Poori",
            "Baingan Bharta",
            "Gutta Curry",
            "Dal Maharani",
            "Chapati",
            "Plain Rice",
            "Sambar",
            "Ice Tea"
        ],
        "dinner": [
            "Khim Chi Salad",
            "Veg Manchurian",
            "Dhaba Dal",
            "Chapati",
            "VEG/Egg Fried/Veg Hakka Noodles",
            "Rasam"
        ]
    },
    {
        "date": "2025-10-24",
        "day": "Friday",
        "breakfast": [
            "Choice of Egg",
            "Cornflakes",
            "Bread + Jam",
            "Bread Pakoda",
            "Tomato Ketchup",
            "Sweet Daliya",
            "Banana",
            "Tea + Coffee",
            "Milk"
        ],
        "lunch": [
            "Papadi Chaat",
            "Gobhi Mutter",
            "Mix Kathol",
            "Dal Palak",
            "Chapati",
            "Plain Rice",
            "Sambar"
        ],
        "dinner": [
            "Lemon + Onion",
            "Mirch Ka Salan",
            "Chole Masala",
            "Puri/Chapati",
            "Jeera Rice",
            "Mix Veg Raita",
            "Chocolate Burfi"
        ]
    },
    {
        "date": "2025-10-25",
        "day": "Saturday",
        "breakfast": [
            "Choice of Egg",
            "Cornflakes",
            "Bread + Jam",
            "Suji Upma",
            "Adrak Chutney",
            "Pineapple",
            "Tea + Coffee",
            "Milk"
        ],
        "lunch": [
            "Green Chutney",
            "Corn Tikki",
            "Kala Channa Masala",
            "Curd/Butter",
            "Gobhi Paratha",
            "Plain Rice",
            "Sambar",
            "Boondi Jaljeera"
        ],
        "dinner": [
            "Green Salad",
            "Veg Makhanwala",
            "Butter Dal Tadka",
            "Chapati",
            "Plain Rice",
            "Rasam",
            "Seeviyaan Kheer"
        ]
    },
    {
        "date": "2025-10-26",
        "day": "Sunday",
        "breakfast": [
            "Choice of Egg",
            "Cornflakes",
            "Bread + Jam",
            "Onion Utappam",
            "Sambhar",
            "Coconut Chuteny",
            "Honey Dew",
            "Tea + Coffee",
            "Milk"
        ],
        "lunch": [
            "Onion Salad",
            "Paneer Lahori",
            "Chicken Biryani",
            "Naan/Chapati",
            "Veg Pulao",
            "Sambar",
            "Boondi Raita"
        ],
        "dinner": [
            "Green Salad",
            "Aloo Gobhi",
            "Mix Dal",
            "Chapati",
            "Plain Rice",
            "Rasam"
        ]
    },
    {
        "date": "2025-10-27",
        "day": "Monday",
        "breakfast": [
            "Choice of Egg",
            "Cornflakes",
            "Bread + Jam",
            "Mutter",
            "Kulcha",
            "Cut Onion Lemon",
            "Papaya",
            "Tea + Coffee",
            "Milk"
        ],
        "lunch": [
            "Green Salad",
            "Raiwale Lauki(dry)",
            "Lobiya Masala",
            "Dal Tadka",
            "Chapati",
            "Plain Rice",
            "Sambar",
            "Sweet Lassi"
        ],
        "dinner": [
            "Mirch Ke Tapore/Lahsun Chutney",
            "Aloo Rassa",
            "Bati/Chapati",
            "Dal Tadka",
            "Plain Rice",
            "Rasam",
            "Churma"
        ]
    },
    {
        "date": "2025-10-28",
        "day": "Tuesday",
        "breakfast": [
            "Mix Sprout",
            "Cornflakes",
            "Bread + Jam",
            "Mix Veg Paratha",
            "Curd",
            "Cut Onion + Lemon",
            "Apple",
            "Tea + Coffee",
            "Milk"
        ],
        "lunch": [
            "Peanut Salad",
            "Soya Handi",
            "Veg Kofta Curry",
            "Moong Dal Tadka",
            "Chapati",
            "Plain Rice",
            "Sambar",
            "Shikanji"
        ],
        "dinner": [
            "Green Salad",
            "Methi Aloo",
            "Red Masoor Dal",
            "Chapati",
            "Jeera Rice",
            "Rasam"
        ]
    },
    {
        "date": "2025-10-29",
        "day": "Wednesday",
        "breakfast": [
            "Choice of Egg",
            "Cornflakes",
            "Bread + Jam",
            "Moong Dal Chilla",
            "Green Chutney",
            "Sweet Daliya",
            "Banana",
            "Tea + Coffee",
            "Milk"
        ],
        "lunch": [
            "Onion Salad",
            "Paneer Korma",
            "Chicken Makhani",
            "Chapati",
            "Veg Pulao",
            "Sambar",
            "Onion Mint Raita"
        ],
        "dinner": [
            "Pasta Salad (Red Sauce)",
            "Veg Kofta Curry",
            "Dhaba Dal",
            "Chapati",
            "Plain Rice",
            "Rasam",
            "Jalebi"
        ]
    },
    {
        "date": "2025-10-30",
        "day": "Thursday",
        "breakfast": [
            "Choice of Egg",
            "Cornflakes",
            "Bread + Jam",
            "Idli/Sautee Idli",
            "Sambhar",
            "Coconut Chutney",
            "Pineapple",
            "Tea + Coffee",
            "Milk"
        ],
        "lunch": [
            "Fryms",
            "Mix Veg Rajasthani",
            "Kadhi Pakoda",
            "Veg Khichdi",
            "Chapati",
            "Plain Rice",
            "Sambar",
            "Tang"
        ],
        "dinner": [
            "Lemon + Onion",
            "Jeera Aloo",
            "Chole Masala",
            "Puri/Chapati",
            "Jeera Rice",
            "Cucumber Raita",
            "Moong Dal Halwa"
        ]
    },
    {
        "date": "2025-10-31",
        "day": "Friday",
        "breakfast": [
            "Choice of Egg",
            "Cornflakes",
            "Bread + Jam",
            "Poha",
            "Sev",
            "Cut Onion + Lemon",
            "Honey Dew",
            "Tea + Coffee",
            "Milk"
        ],
        "lunch": [
            "Kala Chana Chaat",
            "Aloo Beans Mutter",
            "Palak Corn",
            "Butter Dal",
            "Chapati",
            "Plain Rice",
            "Sambar",
            "Pineapple Raita"
        ],
        "dinner": [
            "Green Salad",
            "Soya Chaap",
            "Dal Makhani",
            "Chapati",
            "Plain Rice",
            "Rasam"
        ]
    }
]
