[
  {
    "date": "2025-02-09",
    "day": "Sunday",
    "breakfast": [
      "Choice of egg",
      "Cornflakes",
      "Bread + jam",
      "Besan chilla",
      "Green chutney",
      "Sweet daliya",
      "Banana",
      "Tea + coffee",
      "Milk"
    ],
    "lunch": [
      "Onion salad",
      "Paneer -puru pasanda ( paneer mewari)",
      "Chicken kaswan ( kuku paka chicken)",
      "Biryani-e-malik ( veg biryani)",
      "Naan / chapati",
      "Boondi raita",
      "Kala kand"
    ],
    "dinner": [
      "Green salad",
      "Gutta curry",
      "Red masoor tadka",
      "Plain rice",
      "Chapati",
      "Rasam"
    ]
  },
  {
    "date": "2025-02-10",
    "day": "Monday",
    "breakfast": [
      "Choice of egg",
      "Cornflakes",
      "Bread + jam",
      "Veg poha",
      "Sev",
      "Lemon + onion",
      "Pineapple",
      "Tea + coffee",
      "Milk"
    ],
    "lunch": [
      "Green salad",
      "Gobhi mutter dry",
      "Rajma rasila",
      "Sabut malkamasoor dal",
      "Chapati",
      "Plain rice",
      "Sambar",
      "Sweet lassi"
    ],
    "dinner": [
      "Green salad",
      "Dahi aloo kashmiri",
      "Dal maharani",
      " chapati",
      "Plain rice",
      "Rasam",
      "Tomato soup"
    ]
  },
  {
    "date": "2025-02-11",
    "day": "Tuesday",
    "breakfast": [
      "Mix sprout",
      "Cornflakes",
      "Bread + jam",
      "Aloo pyaaz paratha",
      "Curd",
      "Pickel",
      "Kinnow",
      "Tea + coffee",
      "Milk"
    ],
    "lunch": [
      "Papapdi chaat",
      "Capsicum pitla",
      "Veg kofta curry",
      "Dal palak",
      "Chapati",
      "Plain rice",
      "Sambar",
      "Masala chacch"
    ],
    "dinner": [
      "Tomato /peanut chutney",
      "Vada",
      "Sambhar",
      "Masala dosa",
      "Tomato rice",
      "Chapati( ltd)"
    ]
  },
  {
    "date": "2025-02-12",
    "day": "Wednesday",
    "breakfast": [
      "Choice of egg",
      "Cornflakes",
      "Bread + jam",
      "Methi thepla ",
      "Curd",
      "Khatti meethi tomato chutney",
      "Banana",
      "Tea + coffee",
      "Milk"
    ],
    "lunch": [
      "Onion salad",
      "Paneer hyderabadi ( mint base green gravy)",
      "Dal makhani",
      "Chapati",
      "Green peas pulao",
      "Mix veg raita",
      "Cookies & cream i/c"
    ],
    "dinner": [
      "Pasta salad",
      "Veg diwani handi",
      "Chana dal tadka",
      "Plain rice",
      "Chapati",
      "Rasam",
      "Hot choco milk"
    ]
  },
  {
    "date": "2025-02-13",
    "day": "Thursday",
    "breakfast": [
      "Choice of egg",
      "Cornflakes",
      "Bread + jam",
      "Bread pakoda",
      "Tomato ketchup ",
      "Sweet daliya",
      "Papaya",
      "Tea + coffee",
      "Milk"
    ],
    "lunch": [
      "Fryms",
      "Aloo rai wala tadka",
      "Kadhi pakoda",
      "Curd rice",
      "Chapati",
      "Plain rice",
      "Sambhar",
      "Shikanji"
    ],
    "dinner": [
      "Lemon + onion",
      "Mirch ka salan",
      "Pindi chole",
      "Bhature/ chapati",
      "Jeera rice",
      "Onion mint raita",
      "Coconut burfi"
    ]
  },
  {
    "date": "2025-02-14",
    "day": "Friday",
    "breakfast": [
      "Choice of egg",
      "Cornflakes",
      "Bread + jam",
      "Misal ",
      "Pav",
      "Lemon + onion",
      "Guava",
      "Tea + coffee",
      "Milk"
    ],
    "lunch": [
      "Bhel with chutney",
      "Tawa veg",
      "Mix kathol",
      "Dal lahsuni",
      "Chapati",
      "Plain rice",
      "Pineapple raita"
    ],
    "dinner": [
      "Mirch ke tapore/ lahsun chutney",
      "Aloo rassa",
      "Dal fry",
      "Bati/ chapati",
      "Plain rice",
      "Rasam",
      "Churma"
    ]
  },
  {
    "date": "2025-02-15",
    "day": "Saturday",
    "breakfast": [
      "Choice of egg",
      "Cornflakes",
      "Bread + jam",
      "Punugulu",
      "Sweet daliya",
      "Adrak chutney",
      "Pineapple",
      "Tea + coffee",
      "Milk"
    ],
    "lunch": [
      "Green chutney",
      "Veg shami kebab",
      "Ragda mutter",
      "Curd /butter",
      "Aloo paraths",
      "Plain rice",
      "Sambar"
    ],
    "dinner": [
      "Green salad",
      "Aloo methi dry",
      "Dhaba dal ",
      "Chapati",
      "Plain rice",
      "Rasam",
      "Malpua rabdi "
    ]
  }
]