[
    {
        "date": "2025-11-01",
        "day": "Saturday",
        "breakfast": [
            "Choice of Egg",
            "Cornflakes",
            "Bread + Jam",
            "Seviyan Upma(batches)",
            "Adrak Chutney",
            "Papaya",
            "Tea + Coffee",
            "Milk"
        ],
        "lunch": [
            "Crispy Corn",
            "Kala Chana Masala",
            "Curd/Butter",
            "Aloo Paratha",
            "Plain Rice",
            "Sambar",
            "Jal Jeera"
        ],
        "dinner": [
            "Green Salad",
            "Mix Veg",
            "Butter Dal",
            "Chapati",
            "Plain Rice"
        ]
    },
    {
        "date": "2025-11-02",
        "day": "Sunday",
        "breakfast": [
            "Choice of Egg",
            "Cornflakes",
            "Bread + Jam",
            "M/S Dosa",
            "Sambhar",
            "Coconut Chutney",
            "Cut Pineapple",
            "Tea + Coffee",
            "Milk"
        ],
        "lunch": [
            "Onion Salad",
            "Paneer Butter M/S",
            "Chicken Home Style",
            "Naan/Chapati(ltd)",
            "Veg Pulao",
            "Mix Veg Raita",
            "Butter S/C Ice Cream"
        ],
        "dinner": [
            "Green Salad",
            "Aloo Gobhi",
            "Dal Lasooni",
            "Chapati",
            "Plain Rice",
            "Cream of Tomato Soup"
        ]
    },
    {
        "date": "2025-11-03",
        "day": "Monday",
        "breakfast": [
            "Choice of Egg",
            "Cornflakes",
            "Bread + Jam",
            "Mix Veg Poha",
            "Sev",
            "Onion + Lemon",
            "Cut Apple",
            "Tea + Coffee",
            "Milk"
        ],
        "lunch": [
            "Green Salad",
            "Lauki Chana Dal",
            "Rajma Masala",
            "Dal Tadka",
            "Chapati",
            "Plain Rice",
            "Sambar",
            "Ice Tea"
        ],
        "dinner": [
            "Green Salad",
            "Bhaji",
            "Dhaba Dal",
            "PAV/Chapati",
            "Plain Rice",
            "Chocolate Burfi"
        ]
    },
    {
        "date": "2025-11-04",
        "day": "Tuesday",
        "breakfast": [
            "Moong Sprout",
            "Cornflakes",
            "Bread + Jam",
            "Gobhi Paratha",
            "Curd",
            "Mix Pickle",
            "Banana",
            "Tea + Coffee",
            "Milk"
        ],
        "lunch": [
            "Roasted Papad",
            "Madrasi Aloo",
            "Kadhi Pakoda",
            "Moong Dal Khichidi",
            "Chapati",
            "Plain Rice",
            "Sambar"
        ],
        "dinner": [
            "Mirchi Tapoorey/Lahsun Chutney",
            "Aloo Rassa",
            "Dal Tadka",
            "Chapati/Batti",
            "Jeera Rice",
            "Chorma"
        ]
    },
    {
        "date": "2025-11-05",
        "day": "Wednesday",
        "breakfast": [
            "Choice of Egg",
            "Cornflakes",
            "Bread + Jam",
            "Masala Sandwich",
            "Sweet Daliya",
            "Tomato Sauce",
            "Honey Dew",
            "Tea + Coffee",
            "Milk"
        ],
        "lunch": [
            "Green Salad",
            "Paneer Tikka Masala",
            "Dhaba Chicken",
            "Tikona Paratha",
            "Peas Pulao",
            "Onion Mint Raita"
        ],
        "dinner": [
            "Aloo Kala Channa Chat",
            "Veg Korma",
            "Mix Dal",
            "Chapati",
            "Plain Rice",
            "Hot Choco Milk"
        ]
    },
    {
        "date": "2025-11-06",
        "day": "Thursday",
        "breakfast": [
            "Choice of Egg",
            "Cornflakes",
            "Bread + Jam",
            "Palak Puri",
            "Aloo Bhaji",
            "Lemon + Onion",
            "Papaya",
            "Tea + Coffee",
            "Milk"
        ],
        "lunch": [
            "Green Salad",
            "Baingan Bharta",
            "Kofta Curry",
            "Dal Panchratan",
            "Chapati",
            "Plain Rice",
            "Sambar"
        ],
        "dinner": [
            "Khimchi Salad",
            "Veg Manchurian",
            "Dal Makhani",
            "Chapati",
            "VEG/Egg Fried Rice",
            "Gulab Jamun"
        ]
    },
    {
        "date": "2025-11-07",
        "day": "Friday",
        "breakfast": [
            "Choice of Egg",
            "Cornflakes",
            "Bread + Jam",
            "Stuffed Kulcha",
            "Sweet Daliya",
            "Tomato Sauce",
            "Cut Pineapple",
            "Tea + Coffee",
            "Milk"
        ],
        "lunch": [
            "Corn Salad ( Sep)",
            "Aloo Palak",
            "Gutta Curry",
            "Dal Lahsuni",
            "Chapati",
            "Plain Rice",
            "Sambar",
            "Pineapple Raita"
        ],
        "dinner": [
            "Green Salad",
            "Aloo Gobhi Adraki",
            "Dal Maharani",
            "Chapati",
            "Plain Rice",
            "Veg Manchow"
        ]
    },
    {
        "date": "2025-11-08",
        "day": "Saturday",
        "breakfast": [
            "Choice of Egg",
            "Cornflakes",
            "Bread + Jam",
            "Veg Upma",
            "Adrak Chutney",
            "Cut Apple",
            "Tea + Coffee",
            "Milk"
        ],
        "lunch": [
            "Crispy Corn",
            "White Mutter M/S",
            "Curd/Butter",
            "Aloo Paratha",
            "Plain Rice",
            "Sambar"
        ],
        "dinner": [
            "Green Salad",
            "Sev Tomato",
            "Dal Panchratan",
            "Chapati",
            "Plain Rice",
            "Veg Clear Soup"
        ]
    },
    {
        "date": "2025-11-09",
        "day": "Sunday",
        "breakfast": [
            "Choice of Egg",
            "Cornflakes",
            "Bread + Jam",
            "M/S Sandwich",
            "Sev",
            "Cut Onion + Lemon",
            "Banana",
            "Tea + Coffee",
            "Milk"
        ],
        "lunch": [
            "Onion Salad",
            "Paneer Handi",
            "Kadhai Chicken",
            "Naan/Chapati(ltd)",
            "Biryani Pulao",
            "Boondi Raita"
        ],
        "dinner": [
            "Green Salad",
            "Methi Malai Mutter",
            "Butter Dal Tadka",
            "Chapati",
            "Plain Rice",
            "Lauki Halwa",
            "Tomato Soup"
        ]
    },
    {
        "date": "2025-11-10",
        "day": "Monday",
        "breakfast": [
            "Choice of Egg",
            "Cornflakes",
            "Bread + Jam",
            "Mix Veg Poha",
            "Sweet Daliya",
            "Tomato Sauce",
            "Honey Dew",
            "Tea + Coffee",
            "Milk"
        ],
        "lunch": [
            "Macaroni Salad (No Cucumber)",
            "Jeera Aloo",
            "Lobiya Masala",
            "Dal Tadka",
            "Chapati",
            "Plain Rice",
            "Sambar"
        ],
        "dinner": [
            "Lemon + Onion",
            "Veg Kohlapuri",
            "Dal Lahsuni",
            "Chapati",
            "Plain Rice",
            "Hot & Sour Soup"
        ]
    },
    {
        "date": "2025-11-11",
        "day": "Tuesday",
        "breakfast": [
            "Moong Sprout",
            "Cornflakes",
            "Bread + Jam",
            "Aloo Pyaaz Paratha",
            "Curd",
            "Mix Pickle",
            "Papaya",
            "Tea + Coffee",
            "Milk"
        ],
        "lunch": [
            "Green Salad",
            "Gobhi Mutter Dry",
            "Palak Corn",
            "Dal Fry",
            "Chapati",
            "Plain Rice",
            "Sambar"
        ],
        "dinner": [
            "Lemon + Onion",
            "Khattta Meetha Pumpkin",
            "Chole Masala",
            "Puri",
            "Jeera Rice",
            "Hot Badam Milk"
        ]
    },
    {
        "date": "2025-11-12",
        "day": "Wednesday",
        "breakfast": [
            "Choice of Egg",
            "Cornflakes",
            "Bread + Jam",
            "Tomato Onion Uttapam",
            "Sambhar",
            "Coconut Chutney",
            "Cut Pineapple",
            "Tea + Coffee",
            "Milk"
        ],
        "lunch": [
            "Green Salad",
            "Paneer Lahori",
            "Dal Makhani",
            "Chapati",
            "Plain Rice",
            "Cucumber Raita",
            "Rajashtani Petha"
        ],
        "dinner": [
            "Papdi Chaat",
            "Dum Aloo",
            "Dal Amritsari",
            "Chapati",
            "Plain Rice",
            "Cream of Palak(garlic Based)"
        ]
    },
    {
        "date": "2025-11-13",
        "day": "Thursday",
        "breakfast": [
            "Choice of Egg",
            "Cornflakes",
            "Bread + Jam",
            "Vada Pav",
            "Sweet Daliya",
            "Green Chutney",
            "Cut Apple",
            "Tea + Coffee",
            "Milk"
        ],
        "lunch": [
            "Green Salad",
            "Aloo Mutter Beans",
            "Chole Masala",
            "Dal Tadka",
            "Chapati",
            "Plain Rice",
            "Sambar"
        ],
        "dinner": [
            "Khimchi Salad",
            "Veg Manchurian",
            "Dal Maharani",
            "Chapati",
            "VEG/Egg Fried Rice",
            "Fruit Custard"
        ]
    },
    {
        "date": "2025-11-14",
        "day": "Friday",
        "breakfast": [
            "Choice of Egg",
            "Cornflakes",
            "Bread + Jam",
            "Veg Poha",
            "Lemon + Onion",
            "Banana",
            "Tea + Coffee",
            "Milk"
        ],
        "lunch": [
            "Fryms",
            "Raw Banana Masala",
            "Kadhi Pakoda",
            "Veg Khichidi",
            "Chapati",
            "Jeera Rice",
            "Sambar"
        ],
        "dinner": [
            "Green Salad",
            "Aloo Gobhi Adraki",
            "Dal Lahsooni",
            "Chapati",
            "Plain Rice",
            "Vegetable Soup"
        ]
    },
    {
        "date": "2025-11-15",
        "day": "Saturday",
        "breakfast": [
            "Choice of Egg",
            "Cornflakes",
            "Bread + Jam",
            "Idli",
            "Sambhar",
            "Coconut Chutney",
            "Honey Dew",
            "Tea + Coffee",
            "Milk"
        ],
        "lunch": [
            "Mix Bhajiya",
            "Green Chutney",
            "Kala Chana Masala",
            "Curd/Butter",
            "Aloo Paratha",
            "Plain Rice",
            "Sambar"
        ],
        "dinner": [
            "Bhel Poori",
            "Veg 65",
            "Arhar Dal Tadka",
            "Chapati",
            "Plain Rice",
            "Moong Dal Halwa",
            "Veg Manchow"
        ]
    }
]
